LICENSE
MANIFEST.in
README.md
requirements.txt
setup.py
django_static_fontawesome/.DS_Store
django_static_fontawesome/__init__.py
django_static_fontawesome/admin.py
django_static_fontawesome/apps.py
django_static_fontawesome/models.py
django_static_fontawesome/tests.py
django_static_fontawesome/views.py
django_static_fontawesome.egg-info/PKG-INFO
django_static_fontawesome.egg-info/SOURCES.txt
django_static_fontawesome.egg-info/dependency_links.txt
django_static_fontawesome.egg-info/not-zip-safe
django_static_fontawesome.egg-info/top_level.txt
django_static_fontawesome/migrations/__init__.py
django_static_fontawesome/static/.DS_Store
django_static_fontawesome/static/fontawesome/.DS_Store
django_static_fontawesome/static/fontawesome/LICENSE.txt
django_static_fontawesome/static/fontawesome/css/all.css
django_static_fontawesome/static/fontawesome/css/all.min.css
django_static_fontawesome/static/fontawesome/css/brands.css
django_static_fontawesome/static/fontawesome/css/brands.min.css
django_static_fontawesome/static/fontawesome/css/fontawesome.css
django_static_fontawesome/static/fontawesome/css/fontawesome.min.css
django_static_fontawesome/static/fontawesome/css/regular.css
django_static_fontawesome/static/fontawesome/css/regular.min.css
django_static_fontawesome/static/fontawesome/css/solid.css
django_static_fontawesome/static/fontawesome/css/solid.min.css
django_static_fontawesome/static/fontawesome/css/svg-with-js.css
django_static_fontawesome/static/fontawesome/css/svg-with-js.min.css
django_static_fontawesome/static/fontawesome/css/v4-font-face.css
django_static_fontawesome/static/fontawesome/css/v4-font-face.min.css
django_static_fontawesome/static/fontawesome/css/v4-shims.css
django_static_fontawesome/static/fontawesome/css/v4-shims.min.css
django_static_fontawesome/static/fontawesome/css/v5-font-face.css
django_static_fontawesome/static/fontawesome/css/v5-font-face.min.css
django_static_fontawesome/static/fontawesome/js/all.js
django_static_fontawesome/static/fontawesome/js/all.min.js
django_static_fontawesome/static/fontawesome/js/brands.js
django_static_fontawesome/static/fontawesome/js/brands.min.js
django_static_fontawesome/static/fontawesome/js/conflict-detection.js
