Metadata-Version: 2.4
Name: django-static-fontawesome
Version: 6.5.2.1
Summary: Django application contain font-awesome static files
Author: rRR0VrFP
Maintainer: rRR0VrFP
License: MIT
Keywords: django admin extentions,django static fontawesome
Classifier: Development Status :: 5 - Production/Stable
Classifier: Intended Audience :: Developers
Classifier: Topic :: Software Development :: Libraries :: Python Modules
Classifier: License :: OSI Approved :: MIT License
Classifier: Programming Language :: Python :: 3
Classifier: Programming Language :: Python :: 3 :: Only
License-File: LICENSE
Dynamic: author
Dynamic: classifier
Dynamic: description
Dynamic: description-content-type
Dynamic: keywords
Dynamic: license
Dynamic: license-file
Dynamic: maintainer
Dynamic: summary
